fails_components_jupyter_interceptor/__init__.py
fails_components_jupyter_interceptor/labextension/_version.py
fails_components_jupyter_interceptor/labextension/package.json
fails_components_jupyter_interceptor/labextension/schemas/@fails-components/jupyter-interceptor/package.json.orig
fails_components_jupyter_interceptor/labextension/static/0.af07703559f1c566d285.js
fails_components_jupyter_interceptor/labextension/static/961.f3e63afd4289ba96cfbe.js
fails_components_jupyter_interceptor/labextension/static/remoteEntry.b1144363ce8f4c5acca7.js
fails_components_jupyter_interceptor/labextension/static/style.js
fails_components_jupyter_interceptor/labextension/static/third-party-licenses.json
fails_components_jupyter_interceptor-0.0.5.data/data/share/jupyter/labextensions/@fails-components/jupyter-interceptor/_version.py
fails_components_jupyter_interceptor-0.0.5.data/data/share/jupyter/labextensions/@fails-components/jupyter-interceptor/package.json
fails_components_jupyter_interceptor-0.0.5.data/data/share/jupyter/labextensions/@fails-components/jupyter-interceptor/schemas/@fails-components/jupyter-interceptor/package.json.orig
fails_components_jupyter_interceptor-0.0.5.data/data/share/jupyter/labextensions/@fails-components/jupyter-interceptor/static/0.af07703559f1c566d285.js
fails_components_jupyter_interceptor-0.0.5.data/data/share/jupyter/labextensions/@fails-components/jupyter-interceptor/static/961.f3e63afd4289ba96cfbe.js
fails_components_jupyter_interceptor-0.0.5.data/data/share/jupyter/labextensions/@fails-components/jupyter-interceptor/static/remoteEntry.b1144363ce8f4c5acca7.js
fails_components_jupyter_interceptor-0.0.5.data/data/share/jupyter/labextensions/@fails-components/jupyter-interceptor/static/style.js
fails_components_jupyter_interceptor-0.0.5.data/data/share/jupyter/labextensions/@fails-components/jupyter-interceptor/static/third-party-licenses.json
fails_components_jupyter_interceptor-0.0.5.dist-info/METADATA
fails_components_jupyter_interceptor-0.0.5.dist-info/WHEEL
fails_components_jupyter_interceptor-0.0.5.dist-info/licenses/LICENSE
fails_components_jupyter_interceptor-0.0.5.dist-info/RECORD
